[{"displayName":"Search","name":"Search","id":"Search","type":"feature","narrative":{"name":"Narrative","text":""},"children":[{"displayName":"Login story","name":"Login story","id":"Login story","type":"story","narrative":{"name":"Narrative","text":""},"parent":"Search"},{"displayName":"Logout story","name":"Logout story","id":"Logout story","type":"story","narrative":{"name":"Narrative","text":""},"parent":"Search"},{"displayName":"Scenario story","name":"Scenario story","id":"Scenario story","type":"story","narrative":{"name":"Narrative","text":""},"parent":"Search"},{"displayName":"Search story","name":"Search story","id":"Search story","type":"story","narrative":{"name":"Narrative","text":""},"parent":"Search"}]}]